README.rst
setup.py
mtbconverter/__init__.py
mtbconverter/__main__.py
mtbconverter/argparser.py
mtbconverter/cx_connect.py
mtbconverter/cx_controlled_vocabulary.py
mtbconverter/cx_parameters.py
mtbconverter/cx_profiles.py
mtbconverter/cx_utils.py
mtbconverter/cxxpy.py
mtbconverter/datasetinstance.py
mtbconverter/mtbconverter.py
mtbconverter/mtbconverter_exceptions.py
mtbconverter/mtbfiletype.py
mtbconverter/patientdataset.py
mtbconverter/utils.py
mtbconverter.egg-info/PKG-INFO
mtbconverter.egg-info/SOURCES.txt
mtbconverter.egg-info/dependency_links.txt
mtbconverter.egg-info/requires.txt
mtbconverter.egg-info/top_level.txt