Metadata-Version: 1.1
Name: mtbconverter
Version: 0.1
Summary: A Python command line tool that parses and converts diagnostic variant data for the Molecular Tumor Board at UKT Tübingen.
Home-page: https://github.com/qbicsoftware/qbic.mtbconverter
Author: Sven Fillinger
Author-email: sven.fillinger@qbic.uni-tuebingen.de
License: MIT
Platform: UNKNOWN
Classifier: Programming Language :: Python
Classifier: Programming Language :: Python :: 3.4
Classifier: Programming Language :: Python :: 3.5
Classifier: Intended Audience :: Developers
Classifier: Topic :: Software Development :: Libraries :: Python Modules
Classifier: Topic :: Scientific/Engineering :: Bio-Informatics
Classifier: License :: OSI Approved :: MIT License
